tblib/__init__.py
tblib/cpython.py
tblib/decorators.py
tblib/pickling_support.py
tblib-1.5.0.dist-info/AUTHORS.rst
tblib-1.5.0.dist-info/LICENSE
tblib-1.5.0.dist-info/METADATA
tblib-1.5.0.dist-info/WHEEL
tblib-1.5.0.dist-info/top_level.txt
tblib-1.5.0.dist-info/RECORD
